ids_validator/__init__.py
ids_validator/__main__.py
ids_validator/checks/__init__.py
ids_validator/checks/abstract_checker.py
ids_validator/checks/bulk/__init__.py
ids_validator/checks/constants.py
ids_validator/checks/generic/__init__.py
ids_validator/checks/generic/additional_property.py
ids_validator/checks/generic/athena.py
ids_validator/checks/generic/athena_column_name_resolution_check.py
ids_validator/checks/generic/athena_normalized_field_name.py
ids_validator/checks/generic/datacubes.py
ids_validator/checks/generic/elasticsearch.py
ids_validator/checks/generic/expected.py
ids_validator/checks/generic/required_property.py
ids_validator/checks/generic/reserved_property_names.py
ids_validator/checks/generic/root_node.py
ids_validator/checks/generic/schema_breaking_change.py
ids_validator/checks/generic/type_check.py
ids_validator/checks/rules_checker.py
ids_validator/checks/schema_evolution/merge_compatible.py
ids_validator/checks/schema_evolution/schema_conversion.py
ids_validator/checks/tetra_data/__init__.py
ids_validator/checks/tetra_data/is_tetra_data_checker.py
ids_validator/checks/tetra_data/nodes_checker.py
ids_validator/checks/tetra_data/rules/__init__.py
ids_validator/checks/tetra_data/rules/related_files.py
ids_validator/checks/tetra_data/rules/samples/__init__.py
ids_validator/checks/tetra_data/rules/samples/sample_properties.py
ids_validator/checks/tetra_data/rules/samples/samples_labels.py
ids_validator/checks/tetra_data/rules/samples/samples_location.py
ids_validator/checks/tetra_data/rules/samples/samples_root.py
ids_validator/checks/tetra_data/rules/systems.py
ids_validator/checks/tetra_data/rules/users.py
ids_validator/checks/tetra_data/snake_case.py
ids_validator/helpers/__init__.py
ids_validator/helpers/athena/AthenaDataRetrival.py
ids_validator/helpers/athena/__init__.py
ids_validator/helpers/athena/athena_helper.py
ids_validator/helpers/athena/athena_logger.py
ids_validator/helpers/athena/builders/__init__.py
ts_ids_validator-1.2.0.dist-info/LICENSE
ts_ids_validator-1.2.0.dist-info/METADATA
ts_ids_validator-1.2.0.dist-info/WHEEL
ts_ids_validator-1.2.0.dist-info/entry_points.txt
ts_ids_validator-1.2.0.dist-info/RECORD
