Metadata-Version: 2.3
Name: ts-ids-validator
Version: 1.2.0
Summary: TetraScience IDS artifact validator
License: Apache-2.0
Author: TetraScience
Author-email: developers@tetrascience.com
Requires-Python: >=3.9,<4.0
Classifier: License :: OSI Approved :: Apache Software License
Classifier: Operating System :: OS Independent
Classifier: Programming Language :: Python :: 3
Classifier: Programming Language :: Python :: 3.9
Classifier: Programming Language :: Python :: 3.10
Classifier: Programming Language :: Python :: 3.11
Classifier: Programming Language :: Python :: 3.12
Classifier: Programming Language :: Python :: 3.13
Requires-Dist: deepdiff (>=6.3.0)
Requires-Dist: faker (>18.4.0)
Requires-Dist: gitpython (>=3.1.43,<4.0.0)
Requires-Dist: jsonref
Requires-Dist: jsonschema (>=4.22.0,<5.0.0)
Requires-Dist: pyarrow (>=16.1.0)
Requires-Dist: pydash
Requires-Dist: requests (>=2.31)
Requires-Dist: requests-cache (>=1.2.1,<2.0.0)
Requires-Dist: rfc3986-validator (>=0.1.1,<0.2.0)
Requires-Dist: rich
Requires-Dist: semver (>=3.0.1,<4.0.0)
Requires-Dist: typer (>=0.14.0,<1)
Requires-Dist: typing-extensions (>=4,<5)
Project-URL: Homepage, https://developers.tetrascience.com
